{"stats":{"minecraft:mined":{"minecraft:grass":8,"minecraft:oak_log":1,"minecraft:oak_leaves":2},"minecraft:used":{"call_of_yucutan:chili_pepper":1,"minecraft:oak_planks":4},"minecraft:crafted":{"minecraft:oak_planks":4},"minecraft:picked_up":{"minecraft:wheat_seeds":1,"minecraft:oak_log":1},"minecraft:dropped":{"minecraft:wheat_seeds":1},"minecraft:custom":{"minecraft:time_since_rest":10861,"minecraft:deaths":1,"minecraft:sprint_one_cm":23366,"minecraft:play_time":19031,"minecraft:damage_taken":360,"minecraft:walk_one_cm":30214,"minecraft:walk_under_water_one_cm":462,"minecraft:drop":1,"minecraft:jump":245,"minecraft:leave_game":21,"minecraft:walk_on_water_one_cm":1883,"minecraft:time_since_death":10830,"minecraft:total_world_time":19031,"minecraft:swim_one_cm":2464,"minecraft:fall_one_cm":11473,"minecraft:fly_one_cm":45981}},"DataVersion":3465}